capture_packets.py
capture_packets-0.1.2.dist-info/LICENSE
capture_packets-0.1.2.dist-info/WHEEL
capture_packets-0.1.2.dist-info/METADATA
capture_packets-0.1.2.dist-info/RECORD
