Metadata-Version: 2.1
Name: capture-packets
Version: 0.1.2
Summary: User-friendly packet captures
Author-email: Seth Michael Larson <sethmichaellarson@gmail.com>
Requires-Python: >=3.7
Classifier: License :: OSI Approved :: MIT License
Requires-Dist: scapy>=2.4.5
Requires-Dist: cryptography<37
Project-URL: Home, https://github.com/sethmlarson/capture-packets
